hashitaggi/README.MD
hashitaggi/__init__.py
hashitaggi/requirements.txt
hashitaggi/thirdparty.json
hashitaggi-0.10.dist-info/LICENSE.rst
hashitaggi-0.10.dist-info/METADATA
hashitaggi-0.10.dist-info/WHEEL
hashitaggi-0.10.dist-info/top_level.txt
hashitaggi-0.10.dist-info/RECORD
