Metadata-Version: 2.1
Name: hashitaggi
Version: 0.10
Summary: Get related hashtags
Home-page: https://github.com/hansalemaos/hashitaggi
Author: Johannes Fischer
Author-email: aulasparticularesdealemaosp@gmail.com
License: MIT
Keywords: hashtags
Classifier: Development Status :: 4 - Beta
Classifier: Programming Language :: Python :: 3 :: Only
Classifier: Programming Language :: Python :: 3.10
Classifier: Topic :: Software Development :: Libraries :: Python Modules
Classifier: Topic :: Utilities
License-File: LICENSE.rst
Requires-Dist: PrettyColorPrinter
Requires-Dist: a-pandas-ex-plode-tool
Requires-Dist: a-selenium2df
Requires-Dist: kthread-sleep
Requires-Dist: operagxdriver
Requires-Dist: pandas
Requires-Dist: selenium
Requires-Dist: ujson
